configured_mail_sender/Testing.py
configured_mail_sender/__init__.py
configured_mail_sender/email_builder.py
configured_mail_sender/mail_sender.py
configured_mail_sender/send_email.py
configured_mail_sender/send_email_old.py
configured_mail_sender/smtp_sender.py
configured_mail_sender-2.0.0.dist-info/LICENSE
configured_mail_sender-2.0.0.dist-info/METADATA
configured_mail_sender-2.0.0.dist-info/WHEEL
configured_mail_sender-2.0.0.dist-info/entry_points.txt
configured_mail_sender-2.0.0.dist-info/top_level.txt
configured_mail_sender-2.0.0.dist-info/RECORD
