Metadata-Version: 2.1
Name: configured_mail_sender
Version: 2.0.0
Summary: Simplfy sending email to arbitrary domains
Author-email: David Willcox <daw30410@yahoo.com>
License: MIT License
Project-URL: Homepage, https://github.com/dawillcox/configured_mail_sender
Project-URL: Bug Tracker, https://github.com/dawillcox/configured_mail_sender/issues
Project-URL: Documentation, https://github.com/dawillcox/configured_mail_sender/blob/main/DOCUMENTATION.rst
Project-URL: Change Log, https://github.com/dawillcox/configured_mail_sender/blob/main/CHANGELOG.md
Classifier: Programming Language :: Python :: 3
Classifier: License :: OSI Approved :: MIT License
Classifier: Operating System :: OS Independent
Classifier: Intended Audience :: Developers
Classifier: Natural Language :: English
Requires-Python: >=3.7
License-File: LICENSE
Requires-Dist: combine-settings >=1.1.0
Requires-Dist: platformdirs >=3.10.0
Requires-Dist: filelock >=3.8.0
Requires-Dist: PyYAML >=6.0
